README.rst
setup.py
demo/__init__.py
demo/settings.py
demo/urls.py
demo/wsgi.py
ec2_deploy/__init__.py
ec2_deploy/connections.py
ec2_deploy/fab.py
ec2_deploy/notifications.py
ec2_deploy/utilities.py
ec2_deploy.egg-info/PKG-INFO
ec2_deploy.egg-info/SOURCES.txt
ec2_deploy.egg-info/dependency_links.txt
ec2_deploy.egg-info/requires.txt
ec2_deploy.egg-info/top_level.txt
ec2_deploy/ec2/__init__.py
ec2_deploy/ec2/api.py
server_templates/__init__.py
server_templates/AWS_Ubuntu14_04_LTS/__init__.py
server_templates/AWS_Ubuntu14_04_LTS/gunicorn.conf.py
server_templates/AWS_Ubuntu14_04_LTS/hosts.py
server_templates/AWS_Ubuntu14_04_LTS/hosts_staging.py
server_templates/AWS_Ubuntu14_04_LTS/tasks.py
server_templates/AWS_Ubuntu14_04_LTS/wsgi.py