Metadata-Version: 1.0
Name: ec2-deploy
Version: 0.1.1
Summary: EC2 Deploy is a convenient deployment tool to facilitate code deployment and other tasks to AWS EC2.
Home-page: https://github.com/glynjackson/ec2-deploy
Author: Glyn Jackson
Author-email: me@glynjackson.org
License: The MIT License
Keywords: ec2,deployment,aws,fabric,environment variables,amazon,boto
Platform: UNKNOWN
